texttool
