Metadata-Version: 2.1
Name: textanalyze4sc
Version: 0.7
Summary: 文本分析库，可对文本进行词频统计、词典扩充、情绪分析等
Home-page: https://github.com/martin6336/textanalyze4sc
Author: bqw
Author-email: beerbull@126.com
License: MIT
Keywords: text mining,sentiment analysis,natural language processing,text similarity
